include/rosx_introspection/builtin_types.hpp
include/rosx_introspection/deserializer.hpp
include/rosx_introspection/ros_field.hpp
include/rosx_introspection/ros_message.hpp
include/rosx_introspection/ros_parser.hpp
include/rosx_introspection/ros_type.hpp
include/rosx_introspection/serializer.hpp
include/rosx_introspection/stringtree_leaf.hpp
include/rosx_introspection/tree.hpp
include/rosx_introspection/variant.hpp
include/rosx_introspection/contrib/SmallVector.h
include/rosx_introspection/contrib/msgpack.hpp
include/rosx_introspection/contrib/nanocdr.hpp
include/rosx_introspection/contrib/span.hpp
include/rosx_introspection/details/conversion_impl.hpp
include/rosx_introspection/details/exceptions.hpp
include/rosx_introspection/ros_utils/ros1_helpers.hpp
include/rosx_introspection/ros_utils/ros2_helpers.hpp
lib64/librosx_introspection.a
mcap_bag/__init__.py
mcap_bag/parser.py
mcap_bag/rosx_mcap_adapter.py
mcap_bag/test/test_dataframe_equivalence.py
mcap_bag/test/test_mcap_bag_parser.py
mcap_bag/test/test_module_basic.py
mcap_bag/test/test_nested_array_reconstruction.py
mcap_bag/test/alternate_bagfile/alternate_bagfile_0.mcap
mcap_bag/test/alternate_bagfile/metadata.yaml
mcap_bag/test/bagfile/bagfile_0.mcap
mcap_bag/test/bagfile/metadata.yaml
mcap_bag/test/data/metadata.yaml
mcap_bag/test/data/torque_ripple_data_0.mcap
rosx_introspection/__init__.py
rosx_introspection/rosx_introspection.cpython-310-x86_64-linux-gnu.so
mcap_bag_parser-0.2.3.dist-info/METADATA
mcap_bag_parser-0.2.3.dist-info/WHEEL
mcap_bag_parser-0.2.3.dist-info/RECORD
mcap_bag_parser-0.2.3.dist-info/licenses/LICENSE
