Metadata-Version: 2.2
Name: mcap_bag_parser
Version: 0.2.3
Summary: Parse ROS2 mcap bagfiles efficiently into pandas dataframes, using the rosx_introspection package.
Author: Neal Tanner, Teresa Gadda, Bryan Zhao
Classifier: Programming Language :: Python :: 3
Classifier: License :: OSI Approved :: MIT License
Classifier: Operating System :: OS Independent
Project-URL: Homepage, https://gitlab.com/nealtanner/mcap-bag-parser
Project-URL: Issues, https://gitlab.com/nealtanner/mcap-bag-parser/-/issues
Requires-Python: >=3.10
Requires-Dist: pandas
Requires-Dist: numpy
Requires-Dist: mcap
Requires-Dist: mcap-ros2-support
Requires-Dist: msgpack
